liteframe/__init__.py
liteframe/cli.py
liteframe-0.1.0.dist-info/licenses/LICENSE
liteframe-0.1.0.dist-info/METADATA
liteframe-0.1.0.dist-info/WHEEL
liteframe-0.1.0.dist-info/entry_points.txt
liteframe-0.1.0.dist-info/top_level.txt
liteframe-0.1.0.dist-info/RECORD
