Metadata-Version: 2.4
Name: liteframe
Version: 0.1.0
Summary: SQLite + Pandas framework for data analysis
Author-email: Victor Martins <victor.martins.dpaula@gmail.com>
Maintainer-email: Victor Martins <victor.martins.dpaula@gmail.com>
License-Expression: MIT
Project-URL: Repository, https://github.com/victormpa/liteframe
Keywords: python,package
Classifier: Programming Language :: Python :: 3
Classifier: Operating System :: OS Independent
Requires-Python: >=3.13
License-File: LICENSE
Requires-Dist: click==8.3.0
Provides-Extra: dev
Requires-Dist: pytest>=8.4.2; extra == "dev"
Requires-Dist: flake8; extra == "dev"
Requires-Dist: black; extra == "dev"
Dynamic: license-file
